CHANGELOG.txt
LICENSE.txt
MANIFEST.in
README.txt
__init__.py
calc.py
setup.py
projeto_bibliotecas.egg-info/PKG-INFO
projeto_bibliotecas.egg-info/SOURCES.txt
projeto_bibliotecas.egg-info/dependency_links.txt
projeto_bibliotecas.egg-info/top_level.txt