Metadata-Version: 2.1
Name: projeto-bibliotecas
Version: 0.0.1
Summary: Calculator to test
Home-page: UNKNOWN
Author: Matheus Aranha Lopes
License: MIT
Keywords: calculator
Platform: UNKNOWN
Classifier: Development Status :: 5 - Production/Stable
Classifier: Intended Audience :: Education
Classifier: Operating System :: Microsoft :: Windows :: Windows 10
Classifier: License :: OSI Approved :: MIT License
Classifier: Programming Language :: Python :: 3
License-File: LICENSE.txt
